grrshell/cli/main.py
grrshell/lib/client_monitors.py
grrshell/lib/errors.py
grrshell/lib/flow_args_parsers.py
grrshell/lib/formatters.py
grrshell/lib/grr_shell_client.py
grrshell/lib/grr_shell_emulated_fs.py
grrshell/lib/grr_shell_repl.py
grrshell/lib/utils.py
grrshell/tests/flow_args_parsers_test.py
grrshell/tests/grr_shell_client_test.py
grrshell/tests/grr_shell_emulated_fs_test.py
grrshell/tests/grr_shell_repl_test.py
grrshell/tests/main_test.py
grrshell/tests/testdata/artifact_collect_darwin.zip
grrshell/tests/testdata/artifact_collect_linux.zip
grrshell/tests/testdata/artifact_collect_windows.zip
grrshell/tests/testdata/file_collect_darwin.zip
grrshell/tests/testdata/file_collect_linux.zip
grrshell/tests/testdata/file_collect_windows.zip
grrshell/tests/testdata/file_collect_windows_fat32.zip
grrshell/tests/testdata/getfile_ads.zip
grrshell/tests/testdata/getfile_ads_empty.zip
grrshell/tests/testdata/mock_apiflow_artifactcollector_allfile_running.textproto
grrshell/tests/testdata/mock_apiflow_artifactcollector_allfile_terminated.textproto
grrshell/tests/testdata/mock_apiflow_artifactcollector_multiple.textproto
grrshell/tests/testdata/mock_apiflow_artifactcollector_windowsregkey_running.textproto
grrshell/tests/testdata/mock_apiflow_artifactcollector_wmilogicaldisks_running.textproto
grrshell/tests/testdata/mock_apiflow_clientfilefinder_download_error.textproto
grrshell/tests/testdata/mock_apiflow_clientfilefinder_download_running.textproto
grrshell/tests/testdata/mock_apiflow_clientfilefinder_download_terminated.textproto
grrshell/tests/testdata/mock_apiflow_clientfilefinder_hash_running.textproto
grrshell/tests/testdata/mock_apiflow_clientfilefinder_multiple.textproto
grrshell/tests/testdata/mock_apiflow_collectbrowserhistory.textproto
grrshell/tests/testdata/mock_apiflow_collectfilesbyknownpath_multiple.textproto
grrshell/tests/testdata/mock_apiflow_collectfilesbyknownpath_single.textproto
grrshell/tests/testdata/mock_apiflow_getfile_running.textproto
grrshell-20240704.dist-info/LICENSE
grrshell-20240704.dist-info/METADATA
grrshell-20240704.dist-info/WHEEL
grrshell-20240704.dist-info/entry_points.txt
grrshell-20240704.dist-info/RECORD
