Metadata-Version: 2.1
Name: grrshell
Version: 20240704
Summary: 
Author: Ramo
Author-email: ramoj@google.com
Requires-Python: >=3.9,<4.0
Classifier: Programming Language :: Python :: 3
Classifier: Programming Language :: Python :: 3.9
Classifier: Programming Language :: Python :: 3.10
Classifier: Programming Language :: Python :: 3.11
Classifier: Programming Language :: Python :: 3.12
Requires-Dist: absl-py (>=1.4.0,<2.0.0)
Requires-Dist: grr-api-client (>=3.4.7.post5,<4.0.0)
Requires-Dist: humanize (>=4.7.0,<5.0.0)
Requires-Dist: prompt-toolkit (>=3.0.39,<4.0.0)
